jcl3_DelOro/__init__.py
jcl3_DelOro/jcl3.py
jcl3_DelOro/s3tar.py
jcl3_deloro-0.0.2.dist-info/METADATA
jcl3_deloro-0.0.2.dist-info/WHEEL
jcl3_deloro-0.0.2.dist-info/entry_points.txt
jcl3_deloro-0.0.2.dist-info/licenses/LICENSE
jcl3_deloro-0.0.2.dist-info/RECORD
